drift_monitor/VERSION
drift_monitor/__init__.py
drift_monitor/config.py
drift_monitor/models.py
drift_monitor/py.typed
drift_monitor/queries.py
drift_monitor/schemas.py
drift_monitor/utils.py
drift_monitor-1.1.1.dist-info/LICENSE
drift_monitor-1.1.1.dist-info/METADATA
drift_monitor-1.1.1.dist-info/WHEEL
drift_monitor-1.1.1.dist-info/top_level.txt
drift_monitor-1.1.1.dist-info/RECORD
