Metadata-Version: 2.2
Name: drift-monitor
Version: 1.1.1
Summary: Drift monitoring client in Python.
License: MIT License
Project-URL: Homepage, https://github.com/m-team-kit/drift-watch-client
Project-URL: Bug Tracker, https://github.com/m-team-kit/drift-watch-client/issues
Classifier: Programming Language :: Python :: 3
Classifier: License :: OSI Approved :: MIT License
Classifier: Operating System :: OS Independent
Requires-Python: >=3.10
License-File: LICENSE
Requires-Dist: requests~=2.32.0
Requires-Dist: types-requests~=2.32.0
Requires-Dist: libmytoken~=0.1.0
Requires-Dist: pydantic-settings~=2.8.0
Requires-Dist: pyjwt[crypto]~=2.8.0
Requires-Dist: numpy>=1.26.3
Requires-Dist: marshmallow~=3.23.0
